hw_2/__init__.py
hw_2/task1.py
hw_2/task2.py
alexisomgmhshwgeneratelatex-0.0.1.dist-info/METADATA
alexisomgmhshwgeneratelatex-0.0.1.dist-info/WHEEL
alexisomgmhshwgeneratelatex-0.0.1.dist-info/top_level.txt
alexisomgmhshwgeneratelatex-0.0.1.dist-info/RECORD
