Metadata-Version: 2.1
Name: alexisomgmhshwgeneratelatex
Version: 0.0.1
Summary: ДЗ по Python 
Home-page: UNKNOWN
Author: AlexisOMG
Author-email: alesha-gramazeka@yandex.ru
License: UNKNOWN
Platform: UNKNOWN
Requires-Python: >=3.8
